<?xml version="1.0" encoding="UTF-8" standalone="no"?>
<preflight name="gsbprosp1-22862_1.pdf">
  <executionTimeMS>11824</executionTimeMS>
  <isValid type="PDF/A1-b">false</isValid>
  <errors count="1868">
    <error count="1">
      <code>7.1</code>
      <details>Error on MetaData, Missing Metadata Key in catalog</details>
    </error>
    <error count="1">
      <code>1.0.14</code>
      <details>Syntax error, Object {417:0} has an offset of 0</details>
    </error>
    <error count="1">
      <code>1.0.14</code>
      <details>Syntax error, Object {396:0} has an offset of 0</details>
    </error>
    <error count="1">
      <code>1.0.14</code>
      <details>Syntax error, Object {360:0} has an offset of 0</details>
    </error>
    <error count="1">
      <code>1.0.14</code>
      <details>Syntax error, Object {339:0} has an offset of 0</details>
    </error>
    <error count="1">
      <code>1.0.14</code>
      <details>Syntax error, Object {313:0} has an offset of 0</details>
    </error>
    <error count="1">
      <code>1.0.14</code>
      <details>Syntax error, Object {266:0} has an offset of 0</details>
    </error>
    <error count="1">
      <code>1.0.14</code>
      <details>Syntax error, Object {287:0} has an offset of 0</details>
    </error>
    <error count="1">
      <code>1.0.14</code>
      <details>Syntax error, Object {255:0} has an offset of 0</details>
    </error>
    <error count="1">
      <code>1.0.14</code>
      <details>Syntax error, Object {234:0} has an offset of 0</details>
    </error>
    <error count="1">
      <code>1.0.14</code>
      <details>Syntax error, Object {223:0} has an offset of 0</details>
    </error>
    <error count="1">
      <code>1.0.14</code>
      <details>Syntax error, Object {202:0} has an offset of 0</details>
    </error>
    <error count="1">
      <code>1.0.14</code>
      <details>Syntax error, Object {181:0} has an offset of 0</details>
    </error>
    <error count="1">
      <code>1.0.14</code>
      <details>Syntax error, Object {155:0} has an offset of 0</details>
    </error>
    <error count="1">
      <code>1.0.14</code>
      <details>Syntax error, Object {129:0} has an offset of 0</details>
    </error>
    <error count="1">
      <code>1.0.14</code>
      <details>Syntax error, Object {108:0} has an offset of 0</details>
    </error>
    <error count="1">
      <code>1.0.14</code>
      <details>Syntax error, Object {82:0} has an offset of 0</details>
    </error>
    <error count="1">
      <code>1.0.14</code>
      <details>Syntax error, Object {56:0} has an offset of 0</details>
    </error>
    <error count="1">
      <code>1.0.14</code>
      <details>Syntax error, Object {51:0} has an offset of 0</details>
    </error>
    <error count="1">
      <code>1.0.14</code>
      <details>Syntax error, Object {46:0} has an offset of 0</details>
    </error>
    <error count="1">
      <code>1.0.14</code>
      <details>Syntax error, Object {41:0} has an offset of 0</details>
    </error>
    <error count="1">
      <code>1.0.14</code>
      <details>Syntax error, Object {36:0} has an offset of 0</details>
    </error>
    <error count="1">
      <code>1.0.14</code>
      <details>Syntax error, Object {31:0} has an offset of 0</details>
    </error>
    <error count="1">
      <code>1.0.14</code>
      <details>Syntax error, Object {26:0} has an offset of 0</details>
    </error>
    <error count="1">
      <code>1.0.14</code>
      <details>Syntax error, Object {2:0} has an offset of 0</details>
    </error>
    <error count="17">
      <code>2.4.2</code>
      <details>Invalid Color space, The operator "k" can't be used with RGB Profile</details>
    </error>
    <error count="17">
      <code>2.4.2</code>
      <details>Invalid Color space, The operator "K" can't be used with RGB Profile</details>
    </error>
    <error count="4">
      <code>2.4.3</code>
      <details>Invalid Color space, The operator "g" can't be used without Color Profile</details>
    </error>
    <error count="4">
      <code>2.4.3</code>
      <details>Invalid Color space, The operator "G" can't be used without Color Profile</details>
    </error>
    <error count="162">
      <code>2.4.3</code>
      <details>Invalid Color space, DestOutputProfile is missing</details>
    </error>
    <error count="1438">
      <code>2.4.3</code>
      <details>Invalid Color space, The operator "f*" can't be used without Color Profile</details>
    </error>
    <error count="153">
      <code>2.4.3</code>
      <details>Invalid Color space, The operator "f" can't be used without Color Profile</details>
    </error>
    <error count="35">
      <code>2.4.1</code>
      <details>Invalid Color space, The operator "rg" can't be used with CMYK Profile</details>
    </error>
    <error count="13">
      <code>2.4.1</code>
      <details>Invalid Color space, The operator "RG" can't be used with CMYK Profile</details>
    </error>
  </errors>
</preflight>
