<?xml version="1.0" encoding="UTF-8" standalone="no"?>
<preflight name="eddennis1-122586_1.pdf">
  <executionTimeMS>11866</executionTimeMS>
  <isValid type="PDF/A1-b">false</isValid>
  <errors count="1695">
    <error count="1">
      <code>7.1</code>
      <details>Error on MetaData, Missing Metadata Key in catalog</details>
    </error>
    <error count="24">
      <code>3.1.5</code>
      <details>Invalid Font definition, The Encoding should be missing for the Symbolic TTF</details>
    </error>
    <error count="1">
      <code>1.0.14</code>
      <details>Syntax error, Object {580:0} has an offset of 0</details>
    </error>
    <error count="1">
      <code>1.0.14</code>
      <details>Syntax error, Object {537:0} has an offset of 0</details>
    </error>
    <error count="1">
      <code>1.0.14</code>
      <details>Syntax error, Object {522:0} has an offset of 0</details>
    </error>
    <error count="1">
      <code>1.0.14</code>
      <details>Syntax error, Object {513:0} has an offset of 0</details>
    </error>
    <error count="1">
      <code>1.0.14</code>
      <details>Syntax error, Object {568:0} has an offset of 0</details>
    </error>
    <error count="1">
      <code>1.0.14</code>
      <details>Syntax error, Object {563:0} has an offset of 0</details>
    </error>
    <error count="1">
      <code>1.0.14</code>
      <details>Syntax error, Object {558:0} has an offset of 0</details>
    </error>
    <error count="1">
      <code>1.0.14</code>
      <details>Syntax error, Object {546:0} has an offset of 0</details>
    </error>
    <error count="1">
      <code>1.0.14</code>
      <details>Syntax error, Object {488:0} has an offset of 0</details>
    </error>
    <error count="1">
      <code>1.0.14</code>
      <details>Syntax error, Object {503:0} has an offset of 0</details>
    </error>
    <error count="1">
      <code>1.0.14</code>
      <details>Syntax error, Object {508:0} has an offset of 0</details>
    </error>
    <error count="1">
      <code>1.0.14</code>
      <details>Syntax error, Object {455:0} has an offset of 0</details>
    </error>
    <error count="1">
      <code>1.0.14</code>
      <details>Syntax error, Object {479:0} has an offset of 0</details>
    </error>
    <error count="1">
      <code>1.0.14</code>
      <details>Syntax error, Object {431:0} has an offset of 0</details>
    </error>
    <error count="1">
      <code>1.0.14</code>
      <details>Syntax error, Object {407:0} has an offset of 0</details>
    </error>
    <error count="1">
      <code>1.0.14</code>
      <details>Syntax error, Object {360:0} has an offset of 0</details>
    </error>
    <error count="1">
      <code>1.0.14</code>
      <details>Syntax error, Object {365:0} has an offset of 0</details>
    </error>
    <error count="1">
      <code>1.0.14</code>
      <details>Syntax error, Object {380:0} has an offset of 0</details>
    </error>
    <error count="1">
      <code>1.0.14</code>
      <details>Syntax error, Object {375:0} has an offset of 0</details>
    </error>
    <error count="1">
      <code>1.0.14</code>
      <details>Syntax error, Object {327:0} has an offset of 0</details>
    </error>
    <error count="1">
      <code>1.0.14</code>
      <details>Syntax error, Object {348:0} has an offset of 0</details>
    </error>
    <error count="1">
      <code>1.0.14</code>
      <details>Syntax error, Object {339:0} has an offset of 0</details>
    </error>
    <error count="1">
      <code>1.0.14</code>
      <details>Syntax error, Object {293:0} has an offset of 0</details>
    </error>
    <error count="1">
      <code>1.0.14</code>
      <details>Syntax error, Object {319:0} has an offset of 0</details>
    </error>
    <error count="1">
      <code>1.0.14</code>
      <details>Syntax error, Object {307:0} has an offset of 0</details>
    </error>
    <error count="1">
      <code>1.0.14</code>
      <details>Syntax error, Object {268:0} has an offset of 0</details>
    </error>
    <error count="1">
      <code>1.0.14</code>
      <details>Syntax error, Object {263:0} has an offset of 0</details>
    </error>
    <error count="1">
      <code>1.0.14</code>
      <details>Syntax error, Object {273:0} has an offset of 0</details>
    </error>
    <error count="1">
      <code>1.0.14</code>
      <details>Syntax error, Object {241:0} has an offset of 0</details>
    </error>
    <error count="1">
      <code>1.0.14</code>
      <details>Syntax error, Object {220:0} has an offset of 0</details>
    </error>
    <error count="1">
      <code>1.0.14</code>
      <details>Syntax error, Object {193:0} has an offset of 0</details>
    </error>
    <error count="1">
      <code>1.0.14</code>
      <details>Syntax error, Object {163:0} has an offset of 0</details>
    </error>
    <error count="1">
      <code>1.0.14</code>
      <details>Syntax error, Object {168:0} has an offset of 0</details>
    </error>
    <error count="1">
      <code>1.0.14</code>
      <details>Syntax error, Object {148:0} has an offset of 0</details>
    </error>
    <error count="1">
      <code>1.0.14</code>
      <details>Syntax error, Object {158:0} has an offset of 0</details>
    </error>
    <error count="1">
      <code>1.0.14</code>
      <details>Syntax error, Object {153:0} has an offset of 0</details>
    </error>
    <error count="1">
      <code>1.0.14</code>
      <details>Syntax error, Object {133:0} has an offset of 0</details>
    </error>
    <error count="1">
      <code>1.0.14</code>
      <details>Syntax error, Object {128:0} has an offset of 0</details>
    </error>
    <error count="1">
      <code>1.0.14</code>
      <details>Syntax error, Object {143:0} has an offset of 0</details>
    </error>
    <error count="1">
      <code>1.0.14</code>
      <details>Syntax error, Object {138:0} has an offset of 0</details>
    </error>
    <error count="1">
      <code>1.0.14</code>
      <details>Syntax error, Object {123:0} has an offset of 0</details>
    </error>
    <error count="1">
      <code>1.0.14</code>
      <details>Syntax error, Object {113:0} has an offset of 0</details>
    </error>
    <error count="1">
      <code>1.0.14</code>
      <details>Syntax error, Object {118:0} has an offset of 0</details>
    </error>
    <error count="1">
      <code>1.0.14</code>
      <details>Syntax error, Object {108:0} has an offset of 0</details>
    </error>
    <error count="1">
      <code>1.0.14</code>
      <details>Syntax error, Object {98:0} has an offset of 0</details>
    </error>
    <error count="1">
      <code>1.0.14</code>
      <details>Syntax error, Object {103:0} has an offset of 0</details>
    </error>
    <error count="1">
      <code>1.0.14</code>
      <details>Syntax error, Object {88:0} has an offset of 0</details>
    </error>
    <error count="1">
      <code>1.0.14</code>
      <details>Syntax error, Object {93:0} has an offset of 0</details>
    </error>
    <error count="1">
      <code>1.0.14</code>
      <details>Syntax error, Object {83:0} has an offset of 0</details>
    </error>
    <error count="1">
      <code>1.0.14</code>
      <details>Syntax error, Object {73:0} has an offset of 0</details>
    </error>
    <error count="1">
      <code>1.0.14</code>
      <details>Syntax error, Object {78:0} has an offset of 0</details>
    </error>
    <error count="1">
      <code>1.0.14</code>
      <details>Syntax error, Object {68:0} has an offset of 0</details>
    </error>
    <error count="1">
      <code>1.0.14</code>
      <details>Syntax error, Object {63:0} has an offset of 0</details>
    </error>
    <error count="1">
      <code>1.0.14</code>
      <details>Syntax error, Object {58:0} has an offset of 0</details>
    </error>
    <error count="1">
      <code>1.0.14</code>
      <details>Syntax error, Object {49:0} has an offset of 0</details>
    </error>
    <error count="1">
      <code>1.0.14</code>
      <details>Syntax error, Object {41:0} has an offset of 0</details>
    </error>
    <error count="1">
      <code>1.0.14</code>
      <details>Syntax error, Object {36:0} has an offset of 0</details>
    </error>
    <error count="1">
      <code>1.0.14</code>
      <details>Syntax error, Object {25:0} has an offset of 0</details>
    </error>
    <error count="1">
      <code>1.0.14</code>
      <details>Syntax error, Object {16:0} has an offset of 0</details>
    </error>
    <error count="1">
      <code>1.0.14</code>
      <details>Syntax error, Object {2:0} has an offset of 0</details>
    </error>
    <error count="6">
      <code>2.4.3</code>
      <details>Invalid Color space, The operator "f*" can't be used without Color Profile</details>
    </error>
    <error count="1362">
      <code>2.4.3</code>
      <details>Invalid Color space, The operator "f" can't be used without Color Profile</details>
    </error>
    <error count="85">
      <code>2.4.3</code>
      <details>Invalid Color space, DestOutputProfile is missing</details>
    </error>
    <error count="84">
      <code>2.4.1</code>
      <details>Invalid Color space, The operator "rg" can't be used with CMYK Profile</details>
    </error>
    <error count="73">
      <code>2.4.1</code>
      <details>Invalid Color space, The operator "RG" can't be used with CMYK Profile</details>
    </error>
  </errors>
</preflight>
