<?xml version="1.0" encoding="UTF-8" standalone="no"?>
<preflight name="wessexar1-148906_1.pdf">
  <executionTimeMS>11160</executionTimeMS>
  <isValid type="PDF/A1-b">false</isValid>
  <errors count="1674">
    <error count="10">
      <code>5.1</code>
      <details>Missing field in an annotation definition</details>
    </error>
    <error count="1">
      <code>7.11</code>
      <details>Error on MetaData</details>
    </error>
    <error count="9">
      <code>4.1.2</code>
      <details>Transparency error, ca entry in a ExtGState  is invalid.</details>
    </error>
    <error count="2">
      <code>3.1.5</code>
      <details>Invalid Font definition, The Encoding should be missing for the Symbolic TTF</details>
    </error>
    <error count="1">
      <code>3.1.6</code>
      <details>Invalid Font definition, Width of the character "79" in the font program "OYDAAA+ArialMT"is inconsistent with the width in the PDF dictionary.</details>
    </error>
    <error count="6">
      <code>3.1.6</code>
      <details>Invalid Font definition, Width of the character "48" in the font program "OYDAAA+ArialMT"is inconsistent with the width in the PDF dictionary.</details>
    </error>
    <error count="1">
      <code>3.1.6</code>
      <details>Invalid Font definition, Width of the character "89" in the font program "OYDAAA+ArialMT"is inconsistent with the width in the PDF dictionary.</details>
    </error>
    <error count="1">
      <code>3.1.6</code>
      <details>Invalid Font definition, Width of the character "80" in the font program "OYDAAA+ArialMT"is inconsistent with the width in the PDF dictionary.</details>
    </error>
    <error count="2">
      <code>3.1.6</code>
      <details>Invalid Font definition, Width of the character "56" in the font program "OYDAAA+ArialMT"is inconsistent with the width in the PDF dictionary.</details>
    </error>
    <error count="1">
      <code>3.1.6</code>
      <details>Invalid Font definition, Width of the character "55" in the font program "OYDAAA+ArialMT"is inconsistent with the width in the PDF dictionary.</details>
    </error>
    <error count="1">
      <code>3.1.6</code>
      <details>Invalid Font definition, Width of the character "57" in the font program "OYDAAA+ArialMT"is inconsistent with the width in the PDF dictionary.</details>
    </error>
    <error count="1">
      <code>3.1.6</code>
      <details>Invalid Font definition, Width of the character "74" in the font program "Courier New"is inconsistent with the width in the PDF dictionary.</details>
    </error>
    <error count="2">
      <code>3.1.6</code>
      <details>Invalid Font definition, Width of the character "80" in the font program "Courier New"is inconsistent with the width in the PDF dictionary.</details>
    </error>
    <error count="3">
      <code>3.1.6</code>
      <details>Invalid Font definition, Width of the character "85" in the font program "Courier New"is inconsistent with the width in the PDF dictionary.</details>
    </error>
    <error count="3">
      <code>3.1.6</code>
      <details>Invalid Font definition, Width of the character "73" in the font program "Courier New"is inconsistent with the width in the PDF dictionary.</details>
    </error>
    <error count="1">
      <code>3.1.6</code>
      <details>Invalid Font definition, Width of the character "78" in the font program "Courier New"is inconsistent with the width in the PDF dictionary.</details>
    </error>
    <error count="1">
      <code>3.1.6</code>
      <details>Invalid Font definition, Width of the character "88" in the font program "Courier New"is inconsistent with the width in the PDF dictionary.</details>
    </error>
    <error count="2">
      <code>3.1.6</code>
      <details>Invalid Font definition, Width of the character "70" in the font program "Courier New"is inconsistent with the width in the PDF dictionary.</details>
    </error>
    <error count="3">
      <code>3.1.6</code>
      <details>Invalid Font definition, Width of the character "86" in the font program "Courier New"is inconsistent with the width in the PDF dictionary.</details>
    </error>
    <error count="3">
      <code>3.1.6</code>
      <details>Invalid Font definition, Width of the character "68" in the font program "Courier New"is inconsistent with the width in the PDF dictionary.</details>
    </error>
    <error count="4">
      <code>3.1.6</code>
      <details>Invalid Font definition, Width of the character "17" in the font program "Courier New"is inconsistent with the width in the PDF dictionary.</details>
    </error>
    <error count="3">
      <code>3.1.6</code>
      <details>Invalid Font definition, Width of the character "90" in the font program "Courier New"is inconsistent with the width in the PDF dictionary.</details>
    </error>
    <error count="4">
      <code>3.1.6</code>
      <details>Invalid Font definition, Width of the character "18" in the font program "Courier New"is inconsistent with the width in the PDF dictionary.</details>
    </error>
    <error count="3">
      <code>3.1.6</code>
      <details>Invalid Font definition, Width of the character "83" in the font program "Courier New"is inconsistent with the width in the PDF dictionary.</details>
    </error>
    <error count="2">
      <code>3.1.6</code>
      <details>Invalid Font definition, Width of the character "75" in the font program "Courier New"is inconsistent with the width in the PDF dictionary.</details>
    </error>
    <error count="2">
      <code>3.1.6</code>
      <details>Invalid Font definition, Width of the character "29" in the font program "Courier New"is inconsistent with the width in the PDF dictionary.</details>
    </error>
    <error count="1">
      <code>3.1.6</code>
      <details>Invalid Font definition, Width of the character "92" in the font program "Courier New"is inconsistent with the width in the PDF dictionary.</details>
    </error>
    <error count="1">
      <code>3.1.6</code>
      <details>Invalid Font definition, Width of the character "79" in the font program "Courier New"is inconsistent with the width in the PDF dictionary.</details>
    </error>
    <error count="2">
      <code>3.1.6</code>
      <details>Invalid Font definition, Width of the character "81" in the font program "Courier New"is inconsistent with the width in the PDF dictionary.</details>
    </error>
    <error count="4">
      <code>3.1.6</code>
      <details>Invalid Font definition, Width of the character "82" in the font program "Courier New"is inconsistent with the width in the PDF dictionary.</details>
    </error>
    <error count="5">
      <code>3.1.6</code>
      <details>Invalid Font definition, Width of the character "3" in the font program "Courier New"is inconsistent with the width in the PDF dictionary.</details>
    </error>
    <error count="2">
      <code>3.1.6</code>
      <details>Invalid Font definition, Width of the character "72" in the font program "Courier New"is inconsistent with the width in the PDF dictionary.</details>
    </error>
    <error count="5">
      <code>3.1.6</code>
      <details>Invalid Font definition, Width of the character "87" in the font program "Courier New"is inconsistent with the width in the PDF dictionary.</details>
    </error>
    <error count="4">
      <code>3.1.6</code>
      <details>Invalid Font definition, Width of the character "76" in the font program "Courier New"is inconsistent with the width in the PDF dictionary.</details>
    </error>
    <error count="1">
      <code>3.1.6</code>
      <details>Invalid Font definition, Width of the character "38" in the font program "Courier New"is inconsistent with the width in the PDF dictionary.</details>
    </error>
    <error count="9">
      <code>2.1.7</code>
      <details>Invalid Graphis object, The Group dictionary hasn't Group as Type value</details>
    </error>
    <error count="1">
      <code>2.2.1</code>
      <details>Invalid Graphis transparency, Group has a transparency S entry or the S entry is null.</details>
    </error>
    <error count="16">
      <code>2.4.3</code>
      <details>Invalid Color space, DestOutputProfile is missing</details>
    </error>
    <error count="1092">
      <code>2.4.3</code>
      <details>Invalid Color space, The operator "f" can't be used without Color Profile</details>
    </error>
    <error count="42">
      <code>2.4.1</code>
      <details>Invalid Color space, The operator "RG" can't be used with CMYK Profile</details>
    </error>
    <error count="417">
      <code>2.4.1</code>
      <details>Invalid Color space, The operator "rg" can't be used with CMYK Profile</details>
    </error>
  </errors>
</preflight>
